{
  "timing": {
    "first_week": {
      "monday": [
         {
          "name": "Л Комп мережі",
          "time": "1",
          "teacher": "Агутін М.М.",
          "color": "white",
          "cab": "420"
        },
         {
          "name": "П Теорія прийняття рішень",
          "time": "2",
          "teacher": "доц. Катунiна О.С",
          "color": "white",
          "cab": "423"
        },
        {
          "name": "П Комп мережі",
          "time": "3",
          "teacher": "Агутін М.М.",
          "color": "white",
          "cab": "к.ц."
        }
      ]
    }
  }
}